logging_prometheus/__init__.py
logging_prometheus/handlers.py
logging_prometheus/setup.py
logs_prometheus-1.1.2.dist-info/LICENSE
logs_prometheus-1.1.2.dist-info/METADATA
logs_prometheus-1.1.2.dist-info/WHEEL
logs_prometheus-1.1.2.dist-info/RECORD
