Metadata-Version: 2.1
Name: logs-prometheus
Version: 1.1.2
Summary: logs-based prometheus metrics tool
Home-page: https://gitlab.com/rocshers/python/logs-prometheus
License: MIT
Author: Aleksei Marusich
Author-email: Aleksei.Marusich@rocshers.com
Requires-Python: >=3.8,<4
Classifier: Intended Audience :: Developers
Classifier: Intended Audience :: Information Technology
Classifier: Intended Audience :: System Administrators
Classifier: License :: OSI Approved :: MIT License
Classifier: Programming Language :: Python
Classifier: Programming Language :: Python :: 3
Classifier: Programming Language :: Python :: 3.8
Classifier: Programming Language :: Python :: 3.9
Classifier: Programming Language :: Python :: 3.10
Classifier: Programming Language :: Python :: 3.11
Classifier: Programming Language :: Python :: 3
Classifier: Programming Language :: Python :: 3 :: Only
Classifier: Programming Language :: Python :: 3.8
Classifier: Topic :: Software Development
Classifier: Topic :: Software Development :: Libraries
Classifier: Topic :: Software Development :: Libraries :: Python Modules
Requires-Dist: prometheus-client (>=0.10.0)
Project-URL: Repository, https://gitlab.com/rocshers/python/logs-prometheus
